LICENSE
MANIFEST.in
README.rst
setup.py
django_editor_ymaps.egg-info/PKG-INFO
django_editor_ymaps.egg-info/SOURCES.txt
django_editor_ymaps.egg-info/dependency_links.txt
django_editor_ymaps.egg-info/requires.txt
django_editor_ymaps.egg-info/top_level.txt
djeym/__init__.py
djeym/admin.py
djeym/apps.py
djeym/decorators.py
djeym/forms.py
djeym/globals.py
djeym/middlewares.py
djeym/mixins.py
djeym/models.py
djeym/raw_presets.py
djeym/signals_func.py
djeym/tests.py
djeym/urls.py
djeym/utils.py
djeym/views.py
djeym/widgets.py
djeym/locale/ru/LC_MESSAGES/django.mo
djeym/locale/ru/LC_MESSAGES/djangojs.mo
djeym/management/__init__.py
djeym/management/commands/__init__.py
djeym/management/commands/addmarker.py
djeym/management/commands/exporticons.py
djeym/migrations/0001_initial.py
djeym/migrations/0002_status_alter_generalsettings_buttons_text_color_and_more.py
djeym/migrations/0003_alter_map_title.py
djeym/migrations/__init__.py
djeym/static/colorful/arrow.gif
djeym/static/colorful/colorPicker.css
djeym/static/colorful/jQuery.colorPicker.js
djeym/static/djeym/css/djeym_admin.css
djeym/static/djeym/css/djeym_admin.min.css
djeym/static/djeym/img/amber_arrow.svg
djeym/static/djeym/img/arrow_down.svg
djeym/static/djeym/img/arrow_left.svg
djeym/static/djeym/img/arrow_right.svg
djeym/static/djeym/img/arrow_up.svg
djeym/static/djeym/img/center.svg
djeym/static/djeym/img/cold_fire.svg
djeym/static/djeym/img/default_tile.png
djeym/static/djeym/img/dislike.svg
djeym/static/djeym/img/hint.svg
djeym/static/djeym/img/hot_fire.svg
djeym/static/djeym/img/import.svg
djeym/static/djeym/img/like.svg
djeym/static/djeym/img/loader.gif
djeym/static/djeym/img/logo.svg
djeym/static/djeym/img/no-photo.jpg
djeym/static/djeym/img/offset.svg
djeym/static/djeym/img/plus.svg
djeym/static/djeym/img/spinner.svg
djeym/static/djeym/img/favicons/android-icon-144x144.png
djeym/static/djeym/img/favicons/android-icon-192x192.png
djeym/static/djeym/img/favicons/android-icon-36x36.png
djeym/static/djeym/img/favicons/android-icon-48x48.png
djeym/static/djeym/img/favicons/android-icon-72x72.png
djeym/static/djeym/img/favicons/android-icon-96x96.png
djeym/static/djeym/img/favicons/apple-icon-114x114.png
