Metadata-Version: 2.1
Name: django-editor-ymaps
Version: 2.3.8
Summary: Creating and editing Yandex maps.
Home-page: https://github.com/kebasyaty/django-editor-ymaps
Download-URL: https://github.com/kebasyaty/django-editor-ymaps/tarball/master
Author: kebasyaty
Author-email: kebasyaty@gmail.com
License: MIT License
Keywords: django,yandex,maps,admin,editor
Platform: any
Classifier: Development Status :: 5 - Production/Stable
Classifier: Environment :: Web Environment
Classifier: Natural Language :: Russian
Classifier: Natural Language :: English
Classifier: Framework :: Django
Classifier: Framework :: Django :: 3
Classifier: Framework :: Django :: 4
Classifier: Intended Audience :: Developers
Classifier: License :: OSI Approved :: MIT License
Classifier: Operating System :: OS Independent
Classifier: Programming Language :: Python
Classifier: Programming Language :: Python :: 3.8
Classifier: Programming Language :: Python :: 3.9
Classifier: Programming Language :: Python :: 3.10
Classifier: Programming Language :: Python :: 3.11
Classifier: Topic :: Scientific/Engineering :: GIS
Classifier: Topic :: Internet :: WWW/HTTP :: Dynamic Content
Requires: python (>= 3.8)
Requires: django (>= 3.2.4)
License-File: LICENSE
